{"sentences": [{"sentenceIdx": 574, "originalSentence": "It was a hot, sunny day when Kaylie and Rachel decided to take advantage of their off day and take a trip to the beach.", "elementMap": {"51da9791a69b4c44ba051504eb2a34f2": {"id": "51da9791a69b4c44ba051504eb2a34f2", "parseTree": "(ROOT (S (NP (PRP It)) (VP (VBD was) (NP (NP (DT a) (JJ hot) (, ,) (JJ sunny) (NN day)) (SBAR (WHADVP (WRB when)) (S (NP (NNP Kaylie) (CC and) (NNP Rachel)) (VP (VBD decided) (S (VP (TO to) (VP (VP (VB take) (NP (NP (NN advantage)) (PP (IN of) (NP (PRP$ their) (JJ off) (NN day))))) (CC and) (VP (VB take) (NP (DT a) (NN trip)) (PP (TO to) (NP (DT the) (NN beach)))))))))))) (. .)))", "sentenceIdx": 574, "contextLayer": 0, "simpleContexts": [], "linkedContexts": [], "text": "It was a hot , sunny day when Kaylie and Rachel decided to take advantage of their off day and take a trip to the beach ."}}, "coreferences": [["kaylie and rachel", "the girls", "their", "they"], ["old orchard beach in maine", "the beach"], ["her", "kaylie"], ["her", "rachel", "she"], ["their off day", "this day"]]}, {"sentenceIdx": 575, "originalSentence": "The sun was a blistering, yellow pellet in the sky as the girls drove to Old Orchard Beach in Maine.", "elementMap": {"e079b86fe9f24ebeac3ef6a83b41833c": {"id": "e079b86fe9f24ebeac3ef6a83b41833c", "parseTree": "(ROOT (S (NP (DT The) (NN sun)) (VP (VBD was) (NP (NP (DT a) (VBG blistering) (, ,) (JJ yellow) (NN pellet)) (PP (IN in) (NP (DT the) (NN sky))))) (. .)))", "sentenceIdx": 575, "contextLayer": 0, "simpleContexts": [], "linkedContexts": [{"targetID": "9c2d56d2bce54d178447c3924cf9c16c", "relation": "BACKGROUND"}], "text": "The sun was a blistering , yellow pellet in the sky ."}, "9c2d56d2bce54d178447c3924cf9c16c": {"id": "9c2d56d2bce54d178447c3924cf9c16c", "parseTree": "(ROOT (S (NP (DT The) (NNS girls)) (VP (VBD drove) (PP (TO to) (NP (NP (NNP Old) (NNP Orchard) (NNP Beach)) (PP (IN in) (NP (NNP Maine)))))) (. .)))", "sentenceIdx": 575, "contextLayer": 1, "simpleContexts": [], "linkedContexts": [], "text": "The girls drove to Old Orchard Beach in Maine ."}}, "coreferences": [["kaylie and rachel", "the girls", "their", "they"], ["old orchard beach in maine", "the beach"]]}, {"sentenceIdx": 576, "originalSentence": "The girls saw the crystal clear water turn to deep blue at the horizon as they from the parking lot.", "elementMap": {"bbd8a0911c4c4b93a7f22c2fd6e8f5e5": {"id": "bbd8a0911c4c4b93a7f22c2fd6e8f5e5", "parseTree": "(ROOT (S (NP (DT The) (NNS girls)) (VP (VBD saw)) (. .)))", "sentenceIdx": 576, "contextLayer": 0, "simpleContexts": [{"parseTree": "(ROOT (S (NP (DT This)) (VP (VBD was) (PP (IN from) (NP (DT the) (NN parking) (NN lot)))) (. .)))", "phrase": "(ROOT (FRAG (PP (IN from) (NP (DT the) (NN parking) (NN lot))) (. .)))", "relation": "UNKNOWN_SUBORDINATION", "timeInformation": null, "text": "This was from the parking lot .", "phraseText": "from the parking lot ."}, {"parseTree": "(ROOT (S (NP (DT This)) (VP (VBD was) (PP (IN at) (NP (NP (DT the) (NN horizon)) (PP (IN as) (NP (PRP they)))))) (. .)))", "phrase": "(ROOT (FRAG (PP (IN at) (NP (NP (DT the) (NN horizon)) (PP (IN as) (NP (PRP they))))) (. .)))", "relation": "UNKNOWN_SUBORDINATION", "timeInformation": null, "text": "This was at the horizon as they .", "phraseText": "at the horizon as they ."}, {"parseTree": "(ROOT (S (NP (DT This)) (VP (VBD was) (PP (TO to) (NP (JJ deep) (NN blue)))) (. .)))", "phrase": "(ROOT (FRAG (PP (TO to) (ADJP (RB deep) (JJ blue))) (. .)))", "relation": "UNKNOWN_SUBORDINATION", "timeInformation": null, "text": "This was to deep blue .", "phraseText": "to deep blue ."}], "linkedContexts": [{"targetID": "b5a69634a0994b07b843135516dee8b7", "relation": "UNKNOWN_SUBORDINATION"}], "text": "The girls saw ."}, "b5a69634a0994b07b843135516dee8b7": {"id": "b5a69634a0994b07b843135516dee8b7", "parseTree": "(ROOT (S (NP (DT The) (NN crystal) (JJ clear) (NN water)) (VP (VBP turn)) (. .)))", "sentenceIdx": 576, "contextLayer": 1, "simpleContexts": [], "linkedContexts": [], "text": "The crystal clear water turn ."}}, "coreferences": [["kaylie and rachel", "the girls", "their", "they"], ["old orchard beach in maine", "the beach"]]}, {"sentenceIdx": 577, "originalSentence": "The beach was swarming with people.", "elementMap": {"f133797d154e43ed8dd2815ae23facec": {"id": "f133797d154e43ed8dd2815ae23facec", "parseTree": "(ROOT (S (NP (DT The) (NN beach)) (VP (VBD was) (VP (VBG swarming) (PP (IN with) (NP (NNS people))))) (. .)))", "sentenceIdx": 577, "contextLayer": 0, "simpleContexts": [], "linkedContexts": [], "text": "The beach was swarming with people ."}}, "coreferences": [["old orchard beach in maine", "the beach"]]}, {"sentenceIdx": 578, "originalSentence": "Some people were laying on yellow, orange, white, and pink towels while others could be seen stretching out on chairs.", "elementMap": {"a60e1ba3f3294c01a9f1e5f0a99496ba": {"id": "a60e1ba3f3294c01a9f1e5f0a99496ba", "parseTree": "(ROOT (S (NP (DT Some) (NNS people)) (VP (VBD were) (VP (VBG laying) (PP (IN on) (NP (JJ yellow) (ADJP (JJ white) (, ,) (CC and) (JJ pink)) (NNS towels))))) (. .)))", "sentenceIdx": 578, "contextLayer": 0, "simpleContexts": [{"parseTree": "(ROOT (S (NP (DT This)) (VP (VBD was) (ADJP (JJ orange))) (. .)))", "phrase": "(ROOT (NP (NN orange) (. .)))", "relation": "UNKNOWN_SUBORDINATION", "timeInformation": null, "text": "This was orange .", "phraseText": "orange ."}], "linkedContexts": [{"targetID": "bf16c41f04aa4c9eb93bc3822aabf264", "relation": "CONTRAST"}], "text": "Some people were laying on yellow white , and pink towels ."}, "bf16c41f04aa4c9eb93bc3822aabf264": {"id": "bf16c41f04aa4c9eb93bc3822aabf264", "parseTree": "(ROOT (S (NP (NNS Others)) (VP (MD could) (VP (VB be) (VP (VBN seen) (S (VP (VBG stretching) (PRT (RP out)) (PP (IN on) (NP (NNS chairs)))))))) (. .)))", "sentenceIdx": 578, "contextLayer": 0, "simpleContexts": [], "linkedContexts": [{"targetID": "a60e1ba3f3294c01a9f1e5f0a99496ba", "relation": "CONTRAST"}], "text": "Others could be seen stretching out on chairs ."}}, "coreferences": [["her", "kaylie"]]}, {"sentenceIdx": 579, "originalSentence": "Kaylie decided to lay her towel day in the sand and take a quick nap while Rachel decided to cool off by taking a dip in the ocean.\t", "elementMap": {"d3c60971ec22455cbd065b8fb3f85ed4": {"id": "d3c60971ec22455cbd065b8fb3f85ed4", "parseTree": "(ROOT (S (NP (NNP Kaylie)) (VP (VBD decided) (S (VP (TO to) (VP (VP (VB lay) (NP (PRP$ her) (NN towel) (NN day))) (CC and) (VP (VB take) (NP (DT a) (JJ quick) (NN nap)) (SBAR (IN while) (S (NP (NNP Rachel)) (VP (VBD decided) (S (VP (TO to) (VP (VB cool) (PRT (RP off)) (PP (IN by) (S (VP (VBG taking) (NP (DT a) (NN dip)) (PP (IN in) (NP (DT the) (NN ocean))))))))))))))))) (. .)))", "sentenceIdx": 579, "contextLayer": 0, "simpleContexts": [{"parseTree": "(ROOT (S (NP (DT This)) (VP (VBD was) (PP (IN in) (NP (DT the) (NN sand)))) (. .)))", "phrase": "(ROOT (FRAG (PP (IN in) (NP (DT the) (NN sand))) (. .)))", "relation": "UNKNOWN_SUBORDINATION", "timeInformation": null, "text": "This was in the sand .", "phraseText": "in the sand ."}], "linkedContexts": [], "text": "Kaylie decided to lay her towel day and take a quick nap while Rachel decided to cool off by taking a dip in the ocean ."}}, "coreferences": [["her", "kaylie"], ["her", "rachel", "she"], ["it", "the ocean", "the water"]]}, {"sentenceIdx": 580, "originalSentence": "The sun bounced off the water making it look like a million, tiny crystals.", "elementMap": {"43dc2d8b49bd4aa4974076715ebf0065": {"id": "43dc2d8b49bd4aa4974076715ebf0065", "parseTree": "(ROOT (S (NP (DT The) (NN sun)) (VP (VBD bounced) (PRT (RP off)) (NP (DT the) (NN water))) (. .)))", "sentenceIdx": 580, "contextLayer": 0, "simpleContexts": [], "linkedContexts": [{"targetID": "1cf9c59acb954237a3e32c0d6a19a757", "relation": "IDENTIFYING_DEFINITION"}], "text": "The sun bounced off the water ."}, "1cf9c59acb954237a3e32c0d6a19a757": {"id": "1cf9c59acb954237a3e32c0d6a19a757", "parseTree": "(ROOT (S (NP (DT The) (NN water)) (VP (VBD was) (VP (VBG making) (S (NP (PRP it)) (VP (VB look) (PP (IN like) (NP (QP (DT a) (CD million)))) (, ,) (NP (JJ tiny) (NNS crystals)))))) (. .)))", "sentenceIdx": 580, "contextLayer": 1, "simpleContexts": [], "linkedContexts": [], "text": "The water was making it look like a million , tiny crystals ."}}, "coreferences": [["it", "the ocean", "the water"]]}, {"sentenceIdx": 581, "originalSentence": "Just as Rachel got to the water, a girl with freckles in a purple swimming suit and yellow floaties ran in front of her.", "elementMap": {"107b506f7c1042bab2f22a7dc8d98872": {"id": "107b506f7c1042bab2f22a7dc8d98872", "parseTree": "(ROOT (S (NP (NP (DT A) (NN girl)) (PP (IN with) (NP (NP (NNS freckles)) (PP (IN in) (NP (NP (DT a) (JJ purple) (NN swimming) (NN suit)) (CC and) (NP (JJ yellow) (NNS floaties))))))) (VP (VBD ran) (PP (IN in) (NP (NP (NN front)) (PP (IN of) (NP (PRP her)))))) (. .)))", "sentenceIdx": 581, "contextLayer": 0, "simpleContexts": [], "linkedContexts": [{"targetID": "a16278c651284b04861084e8a9d99f4c", "relation": "BACKGROUND"}], "text": "A girl with freckles in a purple swimming suit and yellow floaties ran in front of her ."}, "a16278c651284b04861084e8a9d99f4c": {"id": "a16278c651284b04861084e8a9d99f4c", "parseTree": "(ROOT (S (NP (NNP Rachel)) (VP (VBD got) (PP (TO to) (NP (DT the) (NN water)))) (. .)))", "sentenceIdx": 581, "contextLayer": 1, "simpleContexts": [], "linkedContexts": [], "text": "Rachel got to the water ."}}, "coreferences": [["her", "rachel", "she"], ["it", "the ocean", "the water"]]}, {"sentenceIdx": 582, "originalSentence": "Her brother, wearing green swim trunks, chased her into the waves.", "elementMap": {"782e36d6597942acba69f5f86e547362": {"id": "782e36d6597942acba69f5f86e547362", "parseTree": "(ROOT (S (NP (PRP$ Her) (NN brother)) (, ,) (S (VP (VBG wearing) (NP (JJ green) (JJ swim) (NNS trunks)))) (, ,) (VP (VBD chased) (NP (PRP her))) (. .)))", "sentenceIdx": 582, "contextLayer": 0, "simpleContexts": [{"parseTree": "(ROOT (S (NP (DT This)) (VP (VBD was) (PP (IN into) (NP (DT the) (NNS waves)))) (. .)))", "phrase": "(ROOT (FRAG (PP (IN into) (NP (DT the) (NNS waves))) (. .)))", "relation": "UNKNOWN_SUBORDINATION", "timeInformation": null, "text": "This was into the waves .", "phraseText": "into the waves ."}], "linkedContexts": [], "text": "Her brother , wearing green swim trunks , chased her ."}}, "coreferences": [["her", "rachel", "she"]]}, {"sentenceIdx": 583, "originalSentence": "She reminisced on the her childhood days of playing with her brothers at the beach.", "elementMap": {"97cf91d285c1400489cacd8d0521340d": {"id": "97cf91d285c1400489cacd8d0521340d", "parseTree": "(ROOT (S (NP (PRP She)) (VP (VBD reminisced) (PP (IN on) (NP (NP (DT the) (PRP$ her) (NN childhood) (NNS days)) (PP (IN of) (S (VP (VBG playing) (PP (IN with) (NP (PRP$ her) (NNS brothers))) (PP (IN at) (NP (DT the) (NN beach))))))))) (. .)))", "sentenceIdx": 583, "contextLayer": 0, "simpleContexts": [], "linkedContexts": [], "text": "She reminisced on the her childhood days of playing with her brothers at the beach ."}}, "coreferences": [["old orchard beach in maine", "the beach"], ["her", "rachel", "she"]]}, {"sentenceIdx": 584, "originalSentence": "As she was leaving the water, she saw four teenagers flying colorful paragliders.", "elementMap": {"317149c0a438471bb71d2ed8aefcdf29": {"id": "317149c0a438471bb71d2ed8aefcdf29", "parseTree": "(ROOT (S (NP (PRP She)) (VP (VBD saw) (NP (CD four) (NNS teenagers))) (. .)))", "sentenceIdx": 584, "contextLayer": 0, "simpleContexts": [], "linkedContexts": [{"targetID": "5c457f5312734273836582487e39a76c", "relation": "IDENTIFYING_DEFINITION"}, {"targetID": "ffec833a317c456a8e688fee4bdcc1a9", "relation": "BACKGROUND"}], "text": "She saw four teenagers ."}, "5c457f5312734273836582487e39a76c": {"id": "5c457f5312734273836582487e39a76c", "parseTree": "(ROOT (S (NP (CD Four) (NNS teenagers)) (VP (VBD were) (VP (VBG flying) (NP (JJ colorful) (NNS paragliders)))) (. .)))", "sentenceIdx": 584, "contextLayer": 1, "simpleContexts": [], "linkedContexts": [], "text": "Four teenagers were flying colorful paragliders ."}, "ffec833a317c456a8e688fee4bdcc1a9": {"id": "ffec833a317c456a8e688fee4bdcc1a9", "parseTree": "(ROOT (S (NP (PRP She)) (VP (VBD was) (VP (VBG leaving) (NP (DT the) (NN water)))) (. .)))", "sentenceIdx": 584, "contextLayer": 1, "simpleContexts": [], "linkedContexts": [], "text": "She was leaving the water ."}}, "coreferences": [["her", "rachel", "she"], ["it", "the ocean", "the water"]]}, {"sentenceIdx": 585, "originalSentence": "All of her daily anxieties disappeared for this day.", "elementMap": {"f5b65de77929424ba4d84b33e1190378": {"id": "f5b65de77929424ba4d84b33e1190378", "parseTree": "(ROOT (S (NP (NP (DT All)) (PP (IN of) (NP (PRP$ her) (JJ daily) (NNS anxieties)))) (VP (VBD disappeared) (PP (IN for) (NP (DT this) (NN day)))) (. .)))", "sentenceIdx": 585, "contextLayer": 0, "simpleContexts": [], "linkedContexts": [], "text": "All of her daily anxieties disappeared for this day ."}}, "coreferences": [["her", "rachel", "she"], ["their off day", "this day"]]}, {"sentenceIdx": 586, "originalSentence": "She decided the moment was perfect and closed her eyes to savor the moment before walking up the beach to lay next to Kaylie in the warm sand.", "elementMap": {"4567dccea7d043ca80713366f30669bd": {"id": "4567dccea7d043ca80713366f30669bd", "parseTree": "(ROOT (S (NP (PRP She)) (VP (VBD decided)) (. .)))", "sentenceIdx": 586, "contextLayer": 0, "simpleContexts": [], "linkedContexts": [{"targetID": "58259866c40c4d3b9307501f70f48164", "relation": "UNKNOWN_SUBORDINATION"}, {"targetID": "3bc12c3a061244dbb533cfaae687a5c1", "relation": "LIST"}], "text": "She decided ."}, "58259866c40c4d3b9307501f70f48164": {"id": "58259866c40c4d3b9307501f70f48164", "parseTree": "(ROOT (S (NP (DT The) (NN moment)) (VP (VBD was) (ADJP (JJ perfect))) (. .)))", "sentenceIdx": 586, "contextLayer": 1, "simpleContexts": [], "linkedContexts": [], "text": "The moment was perfect ."}, "3bc12c3a061244dbb533cfaae687a5c1": {"id": "3bc12c3a061244dbb533cfaae687a5c1", "parseTree": "(ROOT (S (NP (PRP She)) (VP (VBD closed) (NP (PRP$ her) (NNS eyes))) (. .)))", "sentenceIdx": 586, "contextLayer": 0, "simpleContexts": [{"parseTree": "(ROOT (S (NP (DT This)) (VP (VBD was) (S (VP (TO to) (VP (VB savor) (NP (DT the) (NN moment)) (PP (IN before) (S (VP (VBG walking) (PRT (RP up)) (NP (DT the) (NN beach) (S (VP (TO to) (VP (VB lay) (ADVP (JJ next) (PP (TO to) (NP (NNP Kaylie)))) (PP (IN in) (NP (DT the) (JJ warm) (NN sand)))))))))))))) (. .)))", "phrase": "(ROOT (S (VP (TO to) (VP (VB savor) (NP (DT the) (NN moment)) (PP (IN before) (S (VP (VBG walking) (PRT (RP up)) (NP (DT the) (NN beach) (S (VP (TO to) (VP (VB lay) (ADVP (JJ next) (PP (TO to) (NP (NNP Kaylie)))) (PP (IN in) (NP (DT the) (JJ warm) (NN sand)))))))))))) (. .)))", "relation": "PURPOSE", "timeInformation": null, "text": "This was to savor the moment before walking up the beach to lay next to Kaylie in the warm sand .", "phraseText": "to savor the moment before walking up the beach to lay next to Kaylie in the warm sand ."}], "linkedContexts": [{"targetID": "4567dccea7d043ca80713366f30669bd", "relation": "LIST"}], "text": "She closed her eyes ."}}, "coreferences": [["old orchard beach in maine", "the beach"], ["her", "kaylie"], ["her", "rachel", "she"]]}]}