{"sentences": [{"sentenceIdx": 3784, "originalSentence": "I don't care what anyone says", "elementMap": {"25893a6484634c639559cd6f741034f8": {"id": "25893a6484634c639559cd6f741034f8", "parseTree": "(ROOT (S (NP (PRP I)) (VP (VBP do) (RB n't) (VP (VB care))) (. .)))", "sentenceIdx": 3784, "contextLayer": 0, "simpleContexts": [], "linkedContexts": [{"targetID": "ef443340b42e42999654e325b6354ab4", "relation": "UNKNOWN_SUBORDINATION"}], "text": "I do n't care ."}, "ef443340b42e42999654e325b6354ab4": {"id": "ef443340b42e42999654e325b6354ab4", "parseTree": "(ROOT (S (NP (NN Anyone)) (VP (VBZ says)) (. .)))", "sentenceIdx": 3784, "contextLayer": 1, "simpleContexts": [], "linkedContexts": [], "text": "Anyone says ."}}, "coreferences": []}, {"sentenceIdx": 3785, "originalSentence": "New England fogs are much thicker than London fogs.", "elementMap": {"66833030072348d48a417ce2c5374998": {"id": "66833030072348d48a417ce2c5374998", "parseTree": "(ROOT (S (NP (NNP New) (NNP England) (NNS fogs)) (VP (VBP are) (NP (NP (RB much) (JJR thicker)) (PP (IN than) (NP (NNP London) (NNS fogs))))) (. .)))", "sentenceIdx": 3785, "contextLayer": 0, "simpleContexts": [], "linkedContexts": [], "text": "New England fogs are much thicker than London fogs ."}}, "coreferences": [["it", "the fog", "the fog over _ _ _ _ _ _ bay"]]}, {"sentenceIdx": 3786, "originalSentence": "The fog over ______ bay is so thick that you could hammer a nail into it and hang a hat on it.", "elementMap": {"d4687fa4caf7492e997d060db5bddf09": {"id": "d4687fa4caf7492e997d060db5bddf09", "parseTree": "(ROOT (S (NP (NP (DT The) (NN fog)) (PP (IN over) (NP (JJ ______) (NN bay)))) (VP (VBZ is) (ADJP (RB so) (JJ thick))) (. .)))", "sentenceIdx": 3786, "contextLayer": 0, "simpleContexts": [], "linkedContexts": [{"targetID": "073b9576f49b49dd8ed78d76c2ffafc2", "relation": "UNKNOWN_SUBORDINATION"}, {"targetID": "8ccaa47678cd49c49c64237d7b9ec660", "relation": "UNKNOWN_SUBORDINATION"}], "text": "The fog over ______ bay is so thick ."}, "073b9576f49b49dd8ed78d76c2ffafc2": {"id": "073b9576f49b49dd8ed78d76c2ffafc2", "parseTree": "(ROOT (S (NP (PRP You)) (VP (MD could) (VP (VB hammer) (NP (DT a) (NN nail)))) (. .)))", "sentenceIdx": 3786, "contextLayer": 1, "simpleContexts": [{"parseTree": "(ROOT (S (NP (DT This)) (VP (VBZ is) (PP (IN into) (NP (PRP it)))) (. .)))", "phrase": "(ROOT (FRAG (PP (IN into) (NP (PRP it))) (. .)))", "relation": "UNKNOWN_SUBORDINATION", "timeInformation": null, "text": "This is into it .", "phraseText": "into it ."}], "linkedContexts": [{"targetID": "8ccaa47678cd49c49c64237d7b9ec660", "relation": "LIST"}], "text": "You could hammer a nail ."}, "8ccaa47678cd49c49c64237d7b9ec660": {"id": "8ccaa47678cd49c49c64237d7b9ec660", "parseTree": "(ROOT (S (NP (PRP You)) (VP (MD could) (VP (VB hang) (NP (DT a) (NN hat)))) (. .)))", "sentenceIdx": 3786, "contextLayer": 1, "simpleContexts": [{"parseTree": "(ROOT (S (NP (DT This)) (VP (VBZ is) (PP (IN on) (NP (PRP it)))) (. .)))", "phrase": "(ROOT (FRAG (PP (IN on) (NP (PRP it))) (. .)))", "relation": "UNKNOWN_SUBORDINATION", "timeInformation": null, "text": "This is on it .", "phraseText": "on it ."}], "linkedContexts": [{"targetID": "073b9576f49b49dd8ed78d76c2ffafc2", "relation": "LIST"}], "text": "You could hang a hat ."}}, "coreferences": [["it", "the fog", "the fog over _ _ _ _ _ _ bay"]]}, {"sentenceIdx": 3787, "originalSentence": "I had a friend who makes a living as fisherman and even he does not go out when the fog is too thick.", "elementMap": {"5342ff7f5dd647c5b077923ff93426d5": {"id": "5342ff7f5dd647c5b077923ff93426d5", "parseTree": "(ROOT (S (NP (PRP I)) (VP (VBD had) (NP (DT a) (NN friend))) (. .)))", "sentenceIdx": 3787, "contextLayer": 0, "simpleContexts": [], "linkedContexts": [{"targetID": "3d7868277ee449adbddd660d8d745671", "relation": "IDENTIFYING_DEFINITION"}, {"targetID": "1eb9b3bc9efb429c85ca9553baa91528", "relation": "LIST"}], "text": "I had a friend ."}, "3d7868277ee449adbddd660d8d745671": {"id": "3d7868277ee449adbddd660d8d745671", "parseTree": "(ROOT (S (NP (DT A) (NN friend)) (VP (VBZ makes) (NP (NP (DT a) (NN living)) (PP (IN as) (NP (NN fisherman))))) (. .)))", "sentenceIdx": 3787, "contextLayer": 1, "simpleContexts": [], "linkedContexts": [], "text": "A friend makes a living as fisherman ."}, "1eb9b3bc9efb429c85ca9553baa91528": {"id": "1eb9b3bc9efb429c85ca9553baa91528", "parseTree": "(ROOT (S (ADVP (RB Even)) (NP (PRP he)) (VP (VBZ does) (RB not) (VP (VB go) (PRT (RP out)))) (. .)))", "sentenceIdx": 3787, "contextLayer": 0, "simpleContexts": [], "linkedContexts": [{"targetID": "051eb82311fa4f73a6e10f138269f95a", "relation": "BACKGROUND"}, {"targetID": "5342ff7f5dd647c5b077923ff93426d5", "relation": "LIST"}], "text": "Even he does not go out ."}, "051eb82311fa4f73a6e10f138269f95a": {"id": "051eb82311fa4f73a6e10f138269f95a", "parseTree": "(ROOT (S (NP (DT The) (NN fog)) (VP (VBZ is) (ADJP (RB too) (JJ thick))) (. .)))", "sentenceIdx": 3787, "contextLayer": 1, "simpleContexts": [], "linkedContexts": [], "text": "The fog is too thick ."}}, "coreferences": [["it", "the fog", "the fog over _ _ _ _ _ _ bay"], ["a friend who makes a living as fisherman", "even he", "he", "her husband", "him", "his"], ["one day", "that day"]]}, {"sentenceIdx": 3788, "originalSentence": "One day he noticed the fog was rolling in and knew he was not going to be able to go out that day.  ", "elementMap": {"eb0a3a9aa26e4c7ba5f9c1dd0e88c899": {"id": "eb0a3a9aa26e4c7ba5f9c1dd0e88c899", "parseTree": "(ROOT (S (NP-TMP (CD One) (NN day)) (NP (PRP he)) (VP (VBD noticed)) (. .)))", "sentenceIdx": 3788, "contextLayer": 0, "simpleContexts": [], "linkedContexts": [{"targetID": "4c361530afc345b6bc732f8b5ea7ab76", "relation": "UNKNOWN_SUBORDINATION"}, {"targetID": "93ae91e86ccd4b339bf110c23336fe5d", "relation": "LIST"}], "text": "One day he noticed ."}, "4c361530afc345b6bc732f8b5ea7ab76": {"id": "4c361530afc345b6bc732f8b5ea7ab76", "parseTree": "(ROOT (S (NP (DT The) (NN fog)) (VP (VBD was) (VP (VBG rolling) (PRT (RP in)))) (. .)))", "sentenceIdx": 3788, "contextLayer": 1, "simpleContexts": [], "linkedContexts": [], "text": "The fog was rolling in ."}, "93ae91e86ccd4b339bf110c23336fe5d": {"id": "93ae91e86ccd4b339bf110c23336fe5d", "parseTree": "(ROOT (S (NP (PRP He)) (VP (VBD was) (RB not) (VP (VBG going) (S (VP (TO to) (VP (VB be) (ADJP (JJ able) (S (VP (TO to) (VP (VB go) (PRT (RP out)) (NP (DT that) (NN day))))))))))) (. .)))", "sentenceIdx": 3788, "contextLayer": 0, "simpleContexts": [{"parseTree": "(ROOT (S (NP (DT This)) (VP (VBD was) (SBAR (WHNP (WP what)) (S (NP (PRP he)) (VP (VBD knew))))) (. .)))", "phrase": "(ROOT (S (NP (PRP he)) (VP (VBD knew)) (. .)))", "relation": "ATTRIBUTION", "timeInformation": null, "text": "This was what he knew .", "phraseText": "he knew ."}], "linkedContexts": [{"targetID": "eb0a3a9aa26e4c7ba5f9c1dd0e88c899", "relation": "LIST"}], "text": "He was not going to be able to go out that day ."}}, "coreferences": [["it", "the fog", "the fog over _ _ _ _ _ _ bay"], ["a friend who makes a living as fisherman", "even he", "he", "her husband", "him", "his"], ["one day", "that day"]]}, {"sentenceIdx": 3789, "originalSentence": "So he decided to shingle his house.  ", "elementMap": {"33eb05fdf8a746b8ae262f45321bcc3c": {"id": "33eb05fdf8a746b8ae262f45321bcc3c", "parseTree": "(ROOT (S (IN So) (NP (PRP he)) (VP (VBD decided) (S (VP (TO to) (VP (VB shingle) (NP (PRP$ his) (NN house)))))) (. .)))", "sentenceIdx": 3789, "contextLayer": 0, "simpleContexts": [], "linkedContexts": [], "text": "So he decided to shingle his house ."}}, "coreferences": [["a friend who makes a living as fisherman", "even he", "he", "her husband", "him", "his"], ["his house", "the house"]]}, {"sentenceIdx": 3790, "originalSentence": "He climbed up in the morning and did not come back down until dinner time.  ", "elementMap": {"2660db9e83c44080907be0305fedddb9": {"id": "2660db9e83c44080907be0305fedddb9", "parseTree": "(ROOT (S (NP (PRP He)) (VP (VBD climbed) (PRT (RP up)) (PP (IN in) (NP (DT the) (NN morning)))) (. .)))", "sentenceIdx": 3790, "contextLayer": 0, "simpleContexts": [], "linkedContexts": [{"targetID": "3d141ae9500745c397963acdb09504ca", "relation": "LIST"}], "text": "He climbed up in the morning ."}, "3d141ae9500745c397963acdb09504ca": {"id": "3d141ae9500745c397963acdb09504ca", "parseTree": "(ROOT (S (NP (PRP He)) (VP (VBD did) (RB not) (VP (VB come) (ADVP (RB back) (RB down)) (PP (IN until) (NP (NN dinner) (NN time))))) (. .)))", "sentenceIdx": 3790, "contextLayer": 0, "simpleContexts": [], "linkedContexts": [{"targetID": "2660db9e83c44080907be0305fedddb9", "relation": "LIST"}], "text": "He did not come back down until dinner time ."}}, "coreferences": []}, {"sentenceIdx": 3791, "originalSentence": "Over dinner he commented to his wife that they sure had a long house.  ", "elementMap": {"64395338bec245ba83bea552dd45e216": {"id": "64395338bec245ba83bea552dd45e216", "parseTree": "(ROOT (S (NP (PRP They)) (ADVP (RB sure)) (VP (VBD had) (NP (DT a) (JJ long) (NN house))) (. .)))", "sentenceIdx": 3791, "contextLayer": 0, "simpleContexts": [{"parseTree": "(ROOT (S (NP (DT This)) (VP (VBD was) (SBAR (WHNP (WP what)) (S (NP (PRP he)) (VP (VBD commented) (PP (TO to) (NP (PRP$ his) (NN wife))) (PP (IN over) (NP (NN dinner))))))) (. .)))", "phrase": "(ROOT (S (NP (PRP he)) (VP (VBD commented) (PP (TO to) (NP (PRP$ his) (NN wife))) (PP (IN over) (NP (NN dinner)))) (. .)))", "relation": "ATTRIBUTION", "timeInformation": null, "text": "This was what he commented to his wife over dinner .", "phraseText": "he commented to his wife over dinner ."}], "linkedContexts": [], "text": "They sure had a long house ."}}, "coreferences": [["a friend who makes a living as fisherman", "even he", "he", "her husband", "him", "his"], ["her", "his wife", "she"]]}, {"sentenceIdx": 3792, "originalSentence": "She looked at him and then went outside.  ", "elementMap": {"609467c2057b4ddfbf57c66b147954df": {"id": "609467c2057b4ddfbf57c66b147954df", "parseTree": "(ROOT (S (NP (PRP She)) (VP (VBD looked) (PP (IN at) (NP (PRP him)))) (. .)))", "sentenceIdx": 3792, "contextLayer": 0, "simpleContexts": [], "linkedContexts": [{"targetID": "627ac38782854c36b2a6aed166693775", "relation": "LIST"}], "text": "She looked at him ."}, "627ac38782854c36b2a6aed166693775": {"id": "627ac38782854c36b2a6aed166693775", "parseTree": "(ROOT (S (NP (PRP She)) (ADVP (RB then)) (VP (VBD went) (ADVP (RB outside))) (. .)))", "sentenceIdx": 3792, "contextLayer": 0, "simpleContexts": [], "linkedContexts": [{"targetID": "609467c2057b4ddfbf57c66b147954df", "relation": "LIST"}], "text": "She then went outside ."}}, "coreferences": [["a friend who makes a living as fisherman", "even he", "he", "her husband", "him", "his"], ["her", "his wife", "she"]]}, {"sentenceIdx": 3793, "originalSentence": "Her hunch had been correct.  ", "elementMap": {"803852b4860c4c56a474854a375c338a": {"id": "803852b4860c4c56a474854a375c338a", "parseTree": "(ROOT (S (NP (PRP$ Her) (NN hunch)) (VP (VBD had) (VP (VBN been) (ADJP (JJ correct)))) (. .)))", "sentenceIdx": 3793, "contextLayer": 0, "simpleContexts": [], "linkedContexts": [], "text": "Her hunch had been correct ."}}, "coreferences": [["his house", "the house"]]}, {"sentenceIdx": 3794, "originalSentence": "The house had been shingled and at the end of the roof her husband had kept on shingling right onto the fog.", "elementMap": {"110fc6f7c5334c00b686b799af4e5a1d": {"id": "110fc6f7c5334c00b686b799af4e5a1d", "parseTree": "(ROOT (S (NP (DT The) (NN house)) (VP (VBD had) (VP (VBN been) (VP (VBN shingled)))) (. .)))", "sentenceIdx": 3794, "contextLayer": 0, "simpleContexts": [], "linkedContexts": [{"targetID": "9ffda04755684566af96d2ec8b717a05", "relation": "LIST"}], "text": "The house had been shingled ."}, "9ffda04755684566af96d2ec8b717a05": {"id": "9ffda04755684566af96d2ec8b717a05", "parseTree": "(ROOT (S (NP (PRP$ Her) (NN husband)) (VP (VBD had) (VP (VBN kept) (PP (IN on) (S (VP (VBG shingling) (ADVP (RB right)) (PP (IN onto) (NP (DT the) (NN fog)))))))) (. .)))", "sentenceIdx": 3794, "contextLayer": 0, "simpleContexts": [{"parseTree": "(ROOT (S (NP (DT This)) (VP (VBD was) (PP (IN at) (NP (NP (DT the) (NN end)) (PP (IN of) (NP (DT the) (NN roof)))))) (. .)))", "phrase": "(ROOT (FRAG (PP (IN at) (NP (NP (DT the) (NN end)) (PP (IN of) (NP (DT the) (NN roof))))) (. .)))", "relation": "UNKNOWN_SUBORDINATION", "timeInformation": null, "text": "This was at the end of the roof .", "phraseText": "at the end of the roof ."}], "linkedContexts": [{"targetID": "110fc6f7c5334c00b686b799af4e5a1d", "relation": "LIST"}], "text": "Her husband had kept on shingling right onto the fog ."}}, "coreferences": [["it", "the fog", "the fog over _ _ _ _ _ _ bay"], ["a friend who makes a living as fisherman", "even he", "he", "her husband", "him", "his"], ["her", "his wife", "she"], ["his house", "the house"]]}]}